Metadata-Version: 2.1
Name: tcmd
Version: 0.0.1
Summary: A tool for listing the most used commands
Home-page: https://github.com/merwin-asm/tcmd
Author: Cactochan
License: UNKNOWN
Keywords: terminal,tcmd,commands,top,list,rank,tools
Platform: any
Classifier: Programming Language :: Python :: 3
License-File: LICENSE
